LICENSE
MANIFEST.in
README.md
pyproject.toml
setup.cfg
setup.py
bin/redun
examples/__init__.py
redun/__init__.py
redun/azure_utils.py
redun/bcoding.py
redun/cli.py
redun/config.py
redun/context.py
redun/db_utils.py
redun/expression.py
redun/federated_tasks.py
redun/file.py
redun/functools.py
redun/glue.py
redun/handle.py
redun/hashing.py
redun/job_array.py
redun/logging.py
redun/namespace.py
redun/promise.py
redun/py.typed
redun/pytest.py
redun/scheduler.py
redun/scheduler_config.py
redun/scripting.py
redun/sphinx.py
redun/tags.py
redun/task.py
redun/tools.py
redun/utils.py
redun/value.py
redun/version.py
redun/visualize.py
redun.egg-info/PKG-INFO
redun.egg-info/SOURCES.txt
redun.egg-info/dependency_links.txt
redun.egg-info/requires.txt
redun.egg-info/top_level.txt
redun.egg-info/zip-safe
redun/backends/__init__.py
redun/backends/base.py
redun/backends/value_store.py
redun/backends/db/__init__.py
redun/backends/db/alembic.ini
redun/backends/db/dataflow.py
redun/backends/db/query.py
redun/backends/db/serializers.py
redun/backends/db/alembic/__init__.py
redun/backends/db/alembic/env.py
redun/backends/db/alembic/versions/0bee3d6dba76_add_updated_time_field.py
redun/backends/db/alembic/versions/30ffbaee18cd_add_task_version_and_backfill_companion_values.py
redun/backends/db/alembic/versions/3b0a6e67cc58_change_timestamps_to_utc.py
redun/backends/db/alembic/versions/647c510a77b1_add_evaluation_model.py
redun/backends/db/alembic/versions/71ec303c90e4_add_id_indexes.py
redun/backends/db/alembic/versions/806f5dcb11bf_initial_schema.py
redun/backends/db/alembic/versions/cc4f663817b6_add_tag_models.py
redun/backends/db/alembic/versions/cd2d53191748_make_job_execution_id_non_nullable.py
redun/backends/db/alembic/versions/d4af139b6f53_add_job_execution_id.py
redun/backends/db/alembic/versions/eb7b95e4e8bf_remove_length_restriction_on_value_type.py
redun/backends/db/alembic/versions/f68b3aaee9cc_add_job_and_value_indexes.py
redun/console/__init__.py
redun/console/app.py
redun/console/parser.py
redun/console/screens.py
redun/console/style.css
redun/console/upstream_screen.py
redun/console/utils.py
redun/console/widgets.py
