Metadata-Version: 2.1
Name: redun
Version: 0.28.0
Summary: Yet another redundant workflow engine.
Home-page: https://github.com/insitro/redun/
Author: Matt Rasmussen
Author-email: rasmus@insitro.com
License: UNKNOWN
Platform: UNKNOWN
Requires-Python: >= 3.8
Provides-Extra: glue
Provides-Extra: k8s
Provides-Extra: viz
Provides-Extra: google-batch
Provides-Extra: azure
Provides-Extra: postgres
